skeleton/cli.py
skeleton/app_name/__init__.py
skeleton/app_name/admin.py
skeleton/app_name/apps.py
skeleton/app_name/crons.py
skeleton/app_name/models.py
skeleton/app_name/tests.py
skeleton/app_name/views.py
skeleton/app_name/api/__init__.py
skeleton/app_name/api/serializers.py
skeleton/app_name/api/urls.py
skeleton/app_name/api/views.py
skeleton/app_name/migrations/0001_initial.py
skeleton/app_name/migrations/__init__.py
skeleton/project_name/.env
skeleton/project_name/.gitignore
skeleton/project_name/Dockerfile
skeleton/project_name/manage.py
skeleton/project_name/requirements.txt
skeleton/project_name/apps/__init__.py
skeleton/project_name/apps/user/__init__.py
skeleton/project_name/apps/user/admin.py
skeleton/project_name/apps/user/apps.py
skeleton/project_name/apps/user/crons.py
skeleton/project_name/apps/user/models.py
skeleton/project_name/apps/user/tests.py
skeleton/project_name/apps/user/views.py
skeleton/project_name/apps/user/api/__init__.py
skeleton/project_name/apps/user/api/serializers.py
skeleton/project_name/apps/user/api/urls.py
skeleton/project_name/apps/user/api/views.py
skeleton/project_name/apps/user/migrations/0001_initial.py
skeleton/project_name/apps/user/migrations/__init__.py
skeleton/project_name/apps/utils/__init__.py
skeleton/project_name/apps/utils/models.py
skeleton/project_name/apps/utils/pagination.py
skeleton/project_name/configs/__init__.py
skeleton/project_name/configs/asgi.py
skeleton/project_name/configs/healthcheck.py
skeleton/project_name/configs/settings.py
skeleton/project_name/configs/urls.py
skeleton/project_name/configs/wsgi.py
dgi_skeleton-0.1.2.dist-info/METADATA
dgi_skeleton-0.1.2.dist-info/WHEEL
dgi_skeleton-0.1.2.dist-info/entry_points.txt
dgi_skeleton-0.1.2.dist-info/top_level.txt
dgi_skeleton-0.1.2.dist-info/RECORD
