Metadata-Version: 2.1
Name: dgi-skeleton
Version: 0.1.2
Summary: A CLI tool to generate Django project skeletons.
Author: PT Dayagagas Internasional
License: MIT
